{"about.md":"PHM4sBRF","appendix_community.md":"bQBMFAsr","basic_advanced_type_silce.md":"Ejq-uwHz","advanced_memory_manage.md":"Sr-1HATp","basic_advanced_type_enum.md":"zxk83Z0x","basic_advanced_type_opaque.md":"z8dZqYG0","basic_basic_type_function.md":"BaZVayAp","basic_basic_type_number.md":"2KgGbU6A","basic_basic_type_char-and-boolean.md":"AXk2SImH","environment_install-environment.md":"6d04lRC6","basic_process_control_switch.md":"1U9oxlTj","basic_advanced_type_pointer.md":"iVcufaCv","basic_define-variable.md":"Zj3-546G","basic_advanced_type_vector.md":"_v_HApse","basic_union.md":"umRW7qkd","advanced_package_management.md":"bfHLpGy6","advanced_type_cast.md":"57kTwJ6d","environment_editor.md":"X1quwN-G","more_zero-type.md":"v_J1lAh7","more_style_guide.md":"z8KzROcl","advanced_comptime.md":"4CdVYD89","environment_zig-command.md":"fyCDnbYw","basic_process_control_defer.md":"bYCTlTTH","what-is-zig.md":"hVwodYLp","more_wasm.md":"PeMvQPZy","appendix_well-known-lib.md":"z0ZojZd1","advanced_assembly.md":"cE_lKMRS","more_atomic.md":"1Hc2q7Gd","basic_advanced_type_array.md":"39TSaDLT","more_reflection.md":"pHy1J06s","basic_process_control_decision.md":"wapChxVg","advanced_async.md":"1c5EciBq","index.md":"9iD15oA4","hello-world.md":"ygFJ-RHn","advanced_interact-with-c.md":"yAXyfrL2","epilogue.md":"sht7FKCY","basic_advanced_type_struct.md":"94VXKiMd","basic_process_control_unreachable.md":"OGt9Jbf6","engineering_unit-test.md":"pa1_a8KL","more_undefined_behavior.md":"g6XUeMxK","engineering_build-system.md":"XgBCH-Cj","prologue.md":"kgeCBKcx","basic_error_handle.md":"zH0361_I","more_miscellaneous.md":"-MX35emN","basic_optional_type.md":"BAT2I6Nm","basic_process_control_loop.md":"PCqHF4Iw"}
