{"advanced_assembly.md":"tsH2OI5z","advanced_interact-with-c.md":"1wYh8SLt","about.md":"olXjgtET","basic_advanced_type_pointer.md":"0qXQcINu","appendix_community.md":"A6iVZplq","advanced_async.md":"RTn1yIqT","environment_editor.md":"_c2l-xSe","advanced_module-system.md":"34Lwed1E","prologue.md":"vZDt7Ou9","basic_error_handle.md":"A8ir2sTb","epilogue.md":"zv23IWcm","advanced_comptime.md":"VxayVm9n","basic_process_control_switch.md":"0L5EEHw8","basic_define-variable.md":"l2uj8iX2","basic_process_control_decision.md":"HWVVuxwQ","basic_basic_type_char-and-boolean.md":"2UV4RmLd","environment_install-environment.md":"F8fYv1NL","basic_advanced_type_enum.md":"DCmtoOds","environment_zig-command.md":"2E_JFVjW","engineering_unit-test.md":"fFNyOkXv","advanced_memory_manage.md":"Pit5Mf8J","basic_process_control_loop.md":"6jVHhjMh","basic_advanced_type_struct.md":"F1KxTXDT","basic_basic_type_number.md":"kOkxrdkX","what-is-zig.md":"J2rEz92P","basic_basic_type_function.md":"Y7gIC5zx","engineering_build-system.md":"cpZi5n1_","basic_advanced_type_array.md":"3VWHjldD","index.md":"hUMjc7Z2","hello-world.md":"Ac3WJPrh","basic_advanced_type_silce.md":"smcZAx-y","basic_union.md":"sVCbl2AJ","advanced_type_cast.md":"QoXopxMl","appendix_well-known-lib.md":"TxO9ql_a","basic_optional_type.md":"fJRg5A40"}
